{
  "annotations": {
    "list": [
      {
        "builtIn": 1,
        "datasource": {
          "type": "datasource",
          "uid": "grafana"
        },
        "enable": true,
        "hide": true,
        "iconColor": "rgba(0, 211, 255, 1)",
        "name": "Annotations & Alerts",
        "type": "dashboard"
      }
    ]
  },
  "editable": true,
  "fiscalYearStartMonth": 0,
  "graphTooltip": 1,
  "id": null,
  "links": [],
  "liveNow": true,
  "panels": [
    {
      "datasource": {
        "type": "prometheus",
        "uid": "PBFA97CFB590B2093"
      },
      "fieldConfig": {
        "defaults": {
          "color": {
            "mode": "thresholds"
          },
          "mappings": [],
          "thresholds": {
            "mode": "absolute",
            "steps": [
              {
                "color": "green",
                "value": null
              },
              {
                "color": "yellow",
                "value": 1
              },
              {
                "color": "red",
                "value": 5
              }
            ]
          },
          "unit": "short"
        }
      },
      "gridPos": {
        "h": 6,
        "w": 4,
        "x": 0,
        "y": 0
      },
      "id": 1,
      "options": {
        "orientation": "auto",
        "reduceOptions": {
          "values": false,
          "calcs": ["lastNotNull"],
          "fields": ""
        },
        "showThresholdLabels": false,
        "showThresholdMarkers": true,
        "text": {}
      },
      "pluginVersion": "10.0.0",
      "targets": [
        {
          "datasource": {
            "type": "prometheus",
            "uid": "PBFA97CFB590B2093"
          },
          "expr": "sum(rate_limiter_override_applied_total) or vector(0)",
          "refId": "A"
        }
      ],
      "title": "Overrides Applied (Total)",
      "type": "gauge"
    },
    {
      "datasource": {
        "type": "prometheus",
        "uid": "PBFA97CFB590B2093"
      },
      "fieldConfig": {
        "defaults": {
          "color": {
            "mode": "thresholds"
          },
          "mappings": [],
          "thresholds": {
            "mode": "absolute",
            "steps": [
              {
                "color": "green",
                "value": null
              },
              {
                "color": "yellow",
                "value": 1
              },
              {
                "color": "red",
                "value": 10
              }
            ]
          },
          "unit": "short"
        }
      },
      "gridPos": {
        "h": 6,
        "w": 4,
        "x": 4,
        "y": 0
      },
      "id": 2,
      "options": {
        "orientation": "auto",
        "reduceOptions": {
          "values": false,
          "calcs": ["lastNotNull"],
          "fields": ""
        },
        "showThresholdLabels": false,
        "showThresholdMarkers": true,
        "text": {}
      },
      "pluginVersion": "10.0.0",
      "targets": [
        {
          "datasource": {
            "type": "prometheus",
            "uid": "PBFA97CFB590B2093"
          },
          "expr": "sum(rate_limiter_abuse_detection_flags_total) or vector(0)",
          "refId": "A"
        }
      ],
      "title": "Abuse Flags (Total)",
      "type": "gauge"
    },
    {
      "datasource": {
        "type": "prometheus",
        "uid": "PBFA97CFB590B2093"
      },
      "fieldConfig": {
        "defaults": {
          "color": {
            "mode": "thresholds"
          },
          "mappings": [
            {
              "options": {
                "0": {
                  "color": "red",
                  "index": 0,
                  "text": "Failed"
                },
                "1": {
                  "color": "green",
                  "index": 1,
                  "text": "Success"
                }
              },
              "type": "value"
            }
          ],
          "thresholds": {
            "mode": "absolute",
            "steps": [
              {
                "color": "red",
                "value": null
              },
              {
                "color": "green",
                "value": 1
              }
            ]
          },
          "unit": "short"
        }
      },
      "gridPos": {
        "h": 6,
        "w": 4,
        "x": 8,
        "y": 0
      },
      "id": 3,
      "options": {
        "orientation": "auto",
        "reduceOptions": {
          "values": false,
          "calcs": ["lastNotNull"],
          "fields": ""
        },
        "showThresholdLabels": false,
        "showThresholdMarkers": false,
        "text": {}
      },
      "pluginVersion": "10.0.0",
      "targets": [
        {
          "datasource": {
            "type": "prometheus",
            "uid": "PBFA97CFB590B2093"
          },
          "expr": "clamp_max(increase(rate_limiter_abuse_detection_job_runs_total{status=\"success\"}[2m]), 1)",
          "refId": "A"
        }
      ],
      "title": "Detection Job Status",
      "type": "gauge"
    },
    {
      "datasource": {
        "type": "prometheus",
        "uid": "PBFA97CFB590B2093"
      },
      "fieldConfig": {
        "defaults": {
          "color": {
            "mode": "thresholds"
          },
          "mappings": [],
          "max": 100,
          "min": 0,
          "thresholds": {
            "mode": "absolute",
            "steps": [
              {
                "color": "green",
                "value": null
              },
              {
                "color": "yellow",
                "value": 50
              },
              {
                "color": "red",
                "value": 80
              }
            ]
          },
          "unit": "percent"
        }
      },
      "gridPos": {
        "h": 6,
        "w": 12,
        "x": 12,
        "y": 0
      },
      "id": 4,
      "options": {
        "orientation": "auto",
        "reduceOptions": {
          "values": false,
          "calcs": ["lastNotNull"],
          "fields": ""
        },
        "showThresholdLabels": false,
        "showThresholdMarkers": true,
        "text": {}
      },
      "pluginVersion": "10.0.0",
      "targets": [
        {
          "datasource": {
            "type": "prometheus",
            "uid": "PBFA97CFB590B2093"
          },
          "expr": "(\n  sum(rate(rate_limiter_requests_total{result=~\"throttled_soft|throttled_hard\"}[1m]))\n  /\n  sum(rate(rate_limiter_requests_total[1m]))\n) * 100",
          "legendFormat": "Global Throttle Rate",
          "refId": "A"
        }
      ],
      "title": "Global Throttle Rate",
      "type": "gauge"
    },
    {
      "datasource": {
        "type": "prometheus",
        "uid": "PBFA97CFB590B2093"
      },
      "fieldConfig": {
        "defaults": {
          "color": {
            "mode": "palette-classic"
          },
          "custom": {
            "axisCenteredZero": false,
            "axisColorMode": "text",
            "axisLabel": "",
            "axisPlacement": "auto",
            "barAlignment": 0,
            "drawStyle": "line",
            "fillOpacity": 10,
            "gradientMode": "none",
            "hideFrom": {
              "tooltip": false,
              "viz": false,
              "legend": false
            },
            "lineInterpolation": "smooth",
            "lineWidth": 2,
            "pointSize": 5,
            "scaleDistribution": {
              "type": "linear"
            },
            "showPoints": "never",
            "spanNulls": true,
            "stacking": {
              "group": "A",
              "mode": "none"
            },
            "thresholdsStyle": {
              "mode": "off"
            }
          },
          "mappings": [],
          "max": 100,
          "min": 0,
          "thresholds": {
            "mode": "absolute",
            "steps": [
              {
                "color": "green",
                "value": null
              }
            ]
          },
          "unit": "percent"
        },
        "overrides": [
          {
            "matcher": {
              "id": "byName",
              "options": "Threshold (50%)"
            },
            "properties": [
              {
                "id": "color",
                "value": {
                  "fixedColor": "red",
                  "mode": "fixed"
                }
              },
              {
                "id": "custom.lineStyle",
                "value": {
                  "dash": [10, 10],
                  "fill": "dash"
                }
              }
            ]
          }
        ]
      },
      "gridPos": {
        "h": 8,
        "w": 12,
        "x": 0,
        "y": 6
      },
      "id": 5,
      "options": {
        "legend": {
          "calcs": ["mean", "lastNotNull", "max"],
          "displayMode": "table",
          "placement": "bottom",
          "showLegend": true
        },
        "tooltip": {
          "mode": "multi",
          "sort": "desc"
        }
      },
      "targets": [
        {
          "datasource": {
            "type": "prometheus",
            "uid": "PBFA97CFB590B2093"
          },
          "expr": "(\n  sum by (tenant_id) (rate(rate_limiter_requests_total{result=~\"throttled_soft|throttled_hard\"}[1m]))\n  /\n  sum by (tenant_id) (rate(rate_limiter_requests_total[1m]))\n) * 100",
          "legendFormat": "{{tenant_id}}",
          "refId": "A"
        },
        {
          "datasource": {
            "type": "prometheus",
            "uid": "PBFA97CFB590B2093"
          },
          "expr": "50",
          "hide": false,
          "legendFormat": "Threshold (50%)",
          "refId": "B"
        }
      ],
      "title": "Throttle Rate by Tenant",
      "type": "timeseries"
    },
    {
      "datasource": {
        "type": "prometheus",
        "uid": "PBFA97CFB590B2093"
      },
      "fieldConfig": {
        "defaults": {
          "color": {
            "mode": "palette-classic"
          },
          "custom": {
            "axisCenteredZero": false,
            "axisColorMode": "text",
            "axisLabel": "",
            "axisPlacement": "auto",
            "barAlignment": 0,
            "drawStyle": "bars",
            "fillOpacity": 80,
            "gradientMode": "none",
            "hideFrom": {
              "tooltip": false,
              "viz": false,
              "legend": false
            },
            "lineInterpolation": "linear",
            "lineWidth": 1,
            "pointSize": 5,
            "scaleDistribution": {
              "type": "linear"
            },
            "showPoints": "never",
            "spanNulls": true,
            "stacking": {
              "group": "A",
              "mode": "normal"
            },
            "thresholdsStyle": {
              "mode": "off"
            }
          },
          "mappings": [],
          "thresholds": {
            "mode": "absolute",
            "steps": [
              {
                "color": "green",
                "value": null
              }
            ]
          },
          "unit": "short"
        },
        "overrides": [
          {
            "matcher": {
              "id": "byName",
              "options": "penalty_multiplier"
            },
            "properties": [
              {
                "id": "color",
                "value": {
                  "fixedColor": "yellow",
                  "mode": "fixed"
                }
              }
            ]
          },
          {
            "matcher": {
              "id": "byName",
              "options": "temporary_ban"
            },
            "properties": [
              {
                "id": "color",
                "value": {
                  "fixedColor": "red",
                  "mode": "fixed"
                }
              }
            ]
          }
        ]
      },
      "gridPos": {
        "h": 8,
        "w": 12,
        "x": 12,
        "y": 6
      },
      "id": 6,
      "options": {
        "legend": {
          "calcs": ["sum"],
          "displayMode": "table",
          "placement": "bottom",
          "showLegend": true
        },
        "tooltip": {
          "mode": "multi",
          "sort": "desc"
        }
      },
      "targets": [
        {
          "datasource": {
            "type": "prometheus",
            "uid": "PBFA97CFB590B2093"
          },
          "expr": "sum by (type) (rate(rate_limiter_override_applied_total[1m])) * 60",
          "legendFormat": "{{type}}",
          "refId": "A"
        }
      ],
      "title": "Overrides Applied by Type (per min)",
      "type": "timeseries"
    },
    {
      "datasource": {
        "type": "prometheus",
        "uid": "PBFA97CFB590B2093"
      },
      "fieldConfig": {
        "defaults": {
          "color": {
            "mode": "palette-classic"
          },
          "custom": {
            "axisCenteredZero": false,
            "axisColorMode": "text",
            "axisLabel": "",
            "axisPlacement": "auto",
            "barAlignment": 0,
            "drawStyle": "bars",
            "fillOpacity": 80,
            "gradientMode": "none",
            "hideFrom": {
              "tooltip": false,
              "viz": false,
              "legend": false
            },
            "lineInterpolation": "linear",
            "lineWidth": 1,
            "pointSize": 5,
            "scaleDistribution": {
              "type": "linear"
            },
            "showPoints": "never",
            "spanNulls": true,
            "stacking": {
              "group": "A",
              "mode": "normal"
            },
            "thresholdsStyle": {
              "mode": "off"
            }
          },
          "mappings": [],
          "thresholds": {
            "mode": "absolute",
            "steps": [
              {
                "color": "green",
                "value": null
              }
            ]
          },
          "unit": "short"
        },
        "overrides": [
          {
            "matcher": {
              "id": "byName",
              "options": "high"
            },
            "properties": [
              {
                "id": "color",
                "value": {
                  "fixedColor": "red",
                  "mode": "fixed"
                }
              }
            ]
          },
          {
            "matcher": {
              "id": "byName",
              "options": "medium"
            },
            "properties": [
              {
                "id": "color",
                "value": {
                  "fixedColor": "orange",
                  "mode": "fixed"
                }
              }
            ]
          }
        ]
      },
      "gridPos": {
        "h": 8,
        "w": 12,
        "x": 0,
        "y": 14
      },
      "id": 7,
      "options": {
        "legend": {
          "calcs": ["sum"],
          "displayMode": "table",
          "placement": "bottom",
          "showLegend": true
        },
        "tooltip": {
          "mode": "multi",
          "sort": "desc"
        }
      },
      "targets": [
        {
          "datasource": {
            "type": "prometheus",
            "uid": "PBFA97CFB590B2093"
          },
          "expr": "sum by (severity) (increase(rate_limiter_abuse_detection_flags_total[5m]))",
          "legendFormat": "{{severity}}",
          "refId": "A"
        }
      ],
      "title": "Abuse Flags by Severity (5m window)",
      "type": "timeseries"
    },
    {
      "datasource": {
        "type": "prometheus",
        "uid": "PBFA97CFB590B2093"
      },
      "fieldConfig": {
        "defaults": {
          "color": {
            "mode": "palette-classic"
          },
          "custom": {
            "axisCenteredZero": false,
            "axisColorMode": "text",
            "axisLabel": "",
            "axisPlacement": "auto",
            "barAlignment": 0,
            "drawStyle": "line",
            "fillOpacity": 10,
            "gradientMode": "none",
            "hideFrom": {
              "tooltip": false,
              "viz": false,
              "legend": false
            },
            "lineInterpolation": "smooth",
            "lineWidth": 2,
            "pointSize": 5,
            "scaleDistribution": {
              "type": "linear"
            },
            "showPoints": "never",
            "spanNulls": true,
            "stacking": {
              "group": "A",
              "mode": "none"
            },
            "thresholdsStyle": {
              "mode": "off"
            }
          },
          "mappings": [],
          "thresholds": {
            "mode": "absolute",
            "steps": [
              {
                "color": "green",
                "value": null
              }
            ]
          },
          "unit": "short"
        },
        "overrides": [
          {
            "matcher": {
              "id": "byName",
              "options": "success"
            },
            "properties": [
              {
                "id": "color",
                "value": {
                  "fixedColor": "green",
                  "mode": "fixed"
                }
              }
            ]
          },
          {
            "matcher": {
              "id": "byName",
              "options": "error"
            },
            "properties": [
              {
                "id": "color",
                "value": {
                  "fixedColor": "red",
                  "mode": "fixed"
                }
              }
            ]
          }
        ]
      },
      "gridPos": {
        "h": 8,
        "w": 12,
        "x": 12,
        "y": 14
      },
      "id": 8,
      "options": {
        "legend": {
          "calcs": ["lastNotNull", "sum"],
          "displayMode": "table",
          "placement": "bottom",
          "showLegend": true
        },
        "tooltip": {
          "mode": "multi",
          "sort": "none"
        }
      },
      "targets": [
        {
          "datasource": {
            "type": "prometheus",
            "uid": "PBFA97CFB590B2093"
          },
          "expr": "sum by (status) (increase(rate_limiter_abuse_detection_job_runs_total[5m]))",
          "legendFormat": "{{status}}",
          "refId": "A"
        }
      ],
      "title": "Detection Job Runs (5m window)",
      "type": "timeseries"
    },
    {
      "datasource": {
        "type": "prometheus",
        "uid": "PBFA97CFB590B2093"
      },
      "fieldConfig": {
        "defaults": {
          "custom": {
            "align": "auto",
            "cellOptions": {
              "type": "auto"
            },
            "inspect": false
          },
          "mappings": [],
          "thresholds": {
            "mode": "absolute",
            "steps": [
              {
                "color": "green",
                "value": null
              }
            ]
          },
          "color": {
            "mode": "thresholds"
          }
        },
        "overrides": [
          {
            "matcher": {
              "id": "byName",
              "options": "Throttle Rate"
            },
            "properties": [
              {
                "id": "unit",
                "value": "percent"
              },
              {
                "id": "custom.cellOptions",
                "value": {
                  "type": "color-background",
                  "mode": "gradient"
                }
              },
              {
                "id": "thresholds",
                "value": {
                  "mode": "absolute",
                  "steps": [
                    {
                      "color": "green",
                      "value": null
                    },
                    {
                      "color": "yellow",
                      "value": 30
                    },
                    {
                      "color": "red",
                      "value": 50
                    }
                  ]
                }
              }
            ]
          },
          {
            "matcher": {
              "id": "byName",
              "options": "Abuse Flags"
            },
            "properties": [
              {
                "id": "custom.cellOptions",
                "value": {
                  "type": "color-background"
                }
              },
              {
                "id": "thresholds",
                "value": {
                  "mode": "absolute",
                  "steps": [
                    {
                      "color": "green",
                      "value": null
                    },
                    {
                      "color": "yellow",
                      "value": 1
                    },
                    {
                      "color": "red",
                      "value": 5
                    }
                  ]
                }
              }
            ]
          }
        ]
      },
      "gridPos": {
        "h": 8,
        "w": 24,
        "x": 0,
        "y": 22
      },
      "id": 9,
      "options": {
        "showHeader": true,
        "cellHeight": "sm",
        "footer": {
          "show": false,
          "reducer": ["sum"],
          "countRows": false,
          "fields": ""
        },
        "frameIndex": 0
      },
      "pluginVersion": "10.0.0",
      "targets": [
        {
          "datasource": {
            "type": "prometheus",
            "uid": "PBFA97CFB590B2093"
          },
          "expr": "(\n  sum by (tenant_id) (rate(rate_limiter_requests_total{result=~\"throttled_soft|throttled_hard\"}[5m]))\n  /\n  sum by (tenant_id) (rate(rate_limiter_requests_total[5m]))\n) * 100 or vector(0)",
          "format": "table",
          "instant": true,
          "legendFormat": "{{tenant_id}}",
          "refId": "A"
        },
        {
          "datasource": {
            "type": "prometheus",
            "uid": "PBFA97CFB590B2093"
          },
          "expr": "sum by (tenant_id) (rate_limiter_abuse_detection_flags_total)",
          "format": "table",
          "hide": false,
          "instant": true,
          "refId": "B"
        }
      ],
      "title": "Tenants at Risk (Top Abusers)",
      "transformations": [
        {
          "id": "merge",
          "options": {}
        },
        {
          "id": "organize",
          "options": {
            "excludeByName": {
              "Time": true
            },
            "indexByName": {
              "tenant_id": 0,
              "Value #A": 1,
              "Value #B": 2
            },
            "renameByName": {
              "Value #A": "Throttle Rate",
              "Value #B": "Abuse Flags",
              "tenant_id": "Tenant ID"
            }
          }
        },
        {
          "id": "sortBy",
          "options": {
            "fields": {},
            "sort": [
              {
                "field": "Throttle Rate",
                "desc": true
              }
            ]
          }
        }
      ],
      "type": "table"
    }
  ],
  "refresh": "5s",
  "schemaVersion": 38,
  "style": "dark",
  "tags": ["rate-limiter", "abuse-detection", "security"],
  "templating": {
    "list": []
  },
  "time": {
    "from": "now-15m",
    "to": "now"
  },
  "timepicker": {
    "refresh_intervals": ["5s", "10s", "30s", "1m", "5m"]
  },
  "timezone": "",
  "title": "Rate Limiter - Abuse Detection",
  "uid": "abuse-detection",
  "version": 1,
  "weekStart": ""
}
